<?xml version="1.0" ?>
<mods xmlns="http://www.loc.gov/mods/v3">
  <identifier type="local">81</identifier>
  <identifier type="sigla">St</identifier>
  <titleInfo>
    <title>Stagrimo Collection</title>
  </titleInfo>
  <abstract>The Stagringmo Collection is located in Zangskar. More detailed information regarding its specific origins, the patrons or communities involved in its creation, and the historical period of its production is not yet available.</abstract>
  <genre>Canonical Collection</genre>
  <originInfo>
    <dateCreated></dateCreated>
  </originInfo>
  <subject>
    <geographic>Stagringmo</geographic>
  </subject>
  <subject>
    <cartographics>
      <coordinates>33.455780, 76.868400
</coordinates>
    </cartographics>
  </subject>
  <note type="handlist" displayLabel="Handlist Available">false</note>
  <note type="images" displayLabel="Images Available">false</note>
  <note type="text" displayLabel="Text Available">false</note>
</mods>
